ffmpeg_media_converter/Converter.py
ffmpeg_media_converter/__init__.py
ffmpeg_media_converter/extensions.py
ffmpeg_media_converter-0.2.1.dist-info/LICENSE
ffmpeg_media_converter-0.2.1.dist-info/METADATA
ffmpeg_media_converter-0.2.1.dist-info/WHEEL
ffmpeg_media_converter-0.2.1.dist-info/top_level.txt
ffmpeg_media_converter-0.2.1.dist-info/RECORD
