Metadata-Version: 2.1
Name: ffmpeg-media-converter
Version: 0.2.1
Summary: Batch media file format converter based on ffmpeg.
Home-page: https://github.com/lc6464/ffmpeg-media-converter
License: Apache License 2.0
Platform: UNKNOWN
